randluck/__init__.py
randluck/random_seed.py
randluck/utils.py
randluck/strategies/__init__.py
randluck/strategies/bazi.py
randluck/strategies/lucky_num.py
randluck-0.0.1.dist-info/LICENSE
randluck-0.0.1.dist-info/METADATA
randluck-0.0.1.dist-info/WHEEL
randluck-0.0.1.dist-info/top_level.txt
randluck-0.0.1.dist-info/RECORD
