Metadata-Version: 2.1
Name: randluck
Version: 0.0.1
Summary: A toolkit for selecting random seed with luck
Home-page: https://github.com/Spico197/random-luck
Author: Tong Zhu
Author-email: tzhu1997@outlook.com
License: UNKNOWN
Platform: UNKNOWN
Classifier: Programming Language :: Python :: 3
Classifier: License :: OSI Approved :: MIT License
Classifier: Operating System :: OS Independent
Requires-Python: >=3.7
Requires-Dist: sxtwl (>=2.0.4)
Requires-Dist: pytz (>=2021.3)
Provides-Extra: dev
Requires-Dist: pytest ; extra == 'dev'
Requires-Dist: flake8 ; extra == 'dev'
Requires-Dist: black ; extra == 'dev'
Requires-Dist: coverage ; extra == 'dev'
